{"generated_at": "2026-07-10 15:14 UTC", "snapshot": {"symbol": "ACI", "fetch_date": "2026-07-10 13:54:04", "name": "Archean Chemical Industries Limited", "sector": "Basic Materials", "industry": "Chemicals", "price": 527.45, "mcap": 6511.8, "pe": 60.976883, "forward_pe": 15.686246, "pb": 3.3663297, "book_value": 156.684, "roe": 5.55, "roa": 3.62, "de": 0.241, "div_yield": 0.48, "net_margin": 9.89, "op_margin": 7.06, "gross_margin": 92.55, "rev_growth": -12.9, "earn_growth": -73.1, "revenue": 10810507264.0, "net_income": 1068593984.0, "total_debt": 4663793152.0, "total_cash": 490728992.0, "free_cashflow": -2703700992.0, "shares_out": 123458394.0, "wk52_high": 727.6, "wk52_low": 483.0, "beta": 0.196}, "statements": {}}