{"generated_at": "2026-07-22 19:29 UTC", "snapshot": {"symbol": "ACL", "fetch_date": "2026-07-15 20:07:53", "name": "Andhra Cements Limited", "sector": "Basic Materials", "industry": "Building Materials", "price": 49.19, "mcap": 453.4, "pe": null, "forward_pe": null, "pb": 5.6152964, "book_value": 8.76, "roe": -59.62, "roa": -3.36, "de": 13.959, "div_yield": null, "net_margin": -15.17, "op_margin": -12.11, "gross_margin": 39.52, "rev_growth": 73.2, "earn_growth": null, "revenue": 4425900032.0, "net_income": -671600000.0, "total_debt": 11270700032.0, "total_cash": 443400000.0, "free_cashflow": -3204687616.0, "shares_out": 92172140.0, "wk52_high": 109.99, "wk52_low": 40.5, "beta": 0.485}, "statements": {"quarterly_results": {"periods": ["2024-12-31", "2025-03-31", "2025-06-30", "2025-12-31", "2026-03-31"], "items": [{"label": "Revenue", "values": [66.3, 89.5, 99.5, 110.3, 154.8]}, {"label": "Gross Profit", "values": [61.4, 83.8, 85.4, 105.1, 139.3]}, {"label": "Operating Profit", "values": [-26.7, -23.6, -10.1, -18.4, -18.3]}, {"label": "EBITDA", "values": [-6.4, -11.9, 7.7, 5.6, 16.5]}, {"label": "Interest", "values": [19.0, 19.7, 20.5, 26.3, 30.2]}, {"label": "Tax", "values": [0.0, 0.0, 0.0, 0.0, -89.3]}, {"label": "Net Profit", "values": [-43.7, -49.9, -29.6, -44.1, 48.5]}, {"label": "EPS (Rs)", "values": [-4.74, -5.41, -3.21, -4.79, 5.26]}]}, "annual_pnl": {"periods": ["2022-03-31", "2023-03-31", "2024-03-31", "2025-03-31", "2026-03-31"], "items": [{"label": "Revenue", "values": [null, 0.0, 265.6, 272.9, 441.2]}, {"label": "Gross Profit", "values": [null, -0.5, 228.8, 228.6, 344.6]}, {"label": "Operating Profit", "values": [null, -70.0, -59.6, -100.6, -65.9]}, {"label": "EBITDA", "values": [null, 945.7, 8.5, -31.7, 20.0]}, {"label": "Interest", "values": [null, 15.2, 59.0, 71.2, 92.0]}, {"label": "Tax", "values": [null, -65.9, -41.3, -22.4, -89.3]}, {"label": "Net Profit", "values": [null, 949.6, -65.6, -152.1, -67.2]}, {"label": "EPS (Rs)", "values": [null, 696.4, -7.12, -16.5, -7.29]}]}, "balance_sheet": {"periods": ["2022-03-31", "2023-03-31", "2024-03-31", "2025-03-31", "2026-03-31"], "items": [{"label": "Total Assets", "values": [null, 908.8, 1079.7, 1144.4, 1420.1]}, {"label": "Equity", "values": [null, 355.2, 296.8, 144.6, 80.7]}, {"label": "Total Debt", "values": [null, 524.9, 675.4, 768.7, 1165.9]}, {"label": "Cash", "values": [null, 43.7, 10.7, 0.2, 0.2]}, {"label": "Inventory", "values": [null, 5.2, 59.2, 63.0, 81.3]}, {"label": "Receivables", "values": [null, 0.0, 38.5, 30.3, 46.4]}]}, "cash_flow": {"periods": ["2022-03-31", "2023-03-31", "2024-03-31", "2025-03-31", "2026-03-31"], "items": [{"label": "Cash from Operations", "values": [null, -1.0, -26.7, 59.5, -25.1]}, {"label": "Cash from Investing", "values": [null, -35.1, -96.0, -80.6, -248.3]}, {"label": "Cash from Financing", "values": [null, 79.8, 89.7, 10.5, 273.5]}, {"label": "Capex", "values": [null, -27.3, -114.0, -84.6, -226.2]}, {"label": "Free Cash Flow", "values": [null, -28.3, -140.7, -25.0, -251.4]}]}}, "documents": {"annual_reports": [{"from": "2025", "to": "2026", "url": "https://nsearchives.nseindia.com/annual_reports/AR_29308_ACL_2025_2026_A_2344095_30052026133555.pdf"}, {"from": "2024", "to": "2025", "url": "https://nsearchives.nseindia.com/annual_reports/AR_26528_ACL_2024_2025_A_06062025220157.pdf"}, {"from": "2023", "to": "2024", "url": "https://nsearchives.nseindia.com/annual_reports/AR_26334_ACL_2023_2024_1810202412393.pdf"}, {"from": "2022", "to": "2023", "url": "https://nsearchives.nseindia.com/annual_reports/AR_21912_ACL_2022_2023_15052023202122_05152023210001.zip"}], "concalls": [], "ratings": []}, "trend": {"annual": {"periods": ["2023-03-31", "2024-03-31", "2025-03-31", "2026-03-31"], "revenue": [0.0, 268.1, 272.9, 441.2], "pat": [949.6, -65.6, -152.1, -67.2], "eps": [696.4, -7.12, -16.5, -7.29], "expenses": [70.0, 398.3, 373.5, 507.0], "ebitda": [945.7, 8.5, -31.7, 20.0], "book_value": [null, 32.2, null, null], "opm": [null, 3.17, -11.61, 4.53], "gpm": [null, 86.26, 83.79, 78.1], "npm": [null, -24.47, -55.74, -15.22], "source": ["yf", "nse", "yf", "yf"]}, "quarterly": {"periods": ["2023-06-30", "2023-09-30", "2023-12-31", "2024-03-31", "2024-06-30", "2024-09-30", "2024-12-31", "2025-03-31", "2025-06-30", "2025-12-31", "2026-03-31"], "revenue": [13.2, 65.2, 97.9, 91.8, 63.4, 54.9, 66.3, 89.5, 99.5, 110.3, 154.8], "pat": [-24.7, -1.0, -21.2, -18.8, -23.6, -34.9, -43.7, -49.9, -29.6, -44.1, 48.5], "eps": [-2.68, -0.11, -2.3, -2.04, -2.56, -37800.88, -4.74, -5.41, -3.21, -4.79, 5.26], "expenses": [51.2, 89.2, 128.9, 129.0, 104.0, 100.9, 112.0, 113.1, 109.7, 128.6, 173.1], "ebitda": [-11.0, 7.8, 4.6, -4.6, -5.4, -10.3, -6.4, -11.9, 7.7, 5.6, 16.5], "book_value": [null, 36.54, null, 32.2, null, 25.86, null, null, null, null, null], "opm": [-83.11, 11.9, 4.68, -5.01, -8.49, -18.7, -9.59, -13.27, 7.73, 5.12, 10.67], "gpm": [null, null, null, null, null, null, 92.55, 93.63, 85.77, 95.29, 89.99], "npm": [-186.82, -1.5, -21.64, -20.45, -37.21, -63.58, -65.93, -55.78, -29.76, -40.03, 31.33], "source": ["nse", "nse", "nse", "nse", "nse", "nse", "nse", "yf", "yf", "yf", "yf"]}}, "shareholding": {"dates": ["2023-09-30", "2023-12-31", "2024-03-31", "2024-06-30", "2024-09-30", "2024-12-31", "2025-03-31", "2025-06-30", "2025-09-30", "2025-12-31", "2026-03-31", "2026-06-30"], "promoter": [95.0, 95.0, 90.0, 90.0, 90.0, 90.0, 90.0, 90.0, 90.0, 90.0, 75.0, 75.0], "public": [5.0, 5.0, 10.0, 10.0, 10.0, 10.0, 10.0, 10.0, 10.0, 10.0, 25.0, 25.0], "employee": [0.0, 0.0, 0.0, 0.0, 0.0, 0.0, 0.0, 0.0, 0.0, 0.0, 0.0, 0.0]}, "prices": {"daily": [["2024-07-15", 98.12, 125808], ["2024-07-16", 98.17, 76655], ["2024-07-18", 97.87, 68829], ["2024-07-19", 94.26, 79961], ["2024-07-22", 94.3, 32338], ["2024-07-23", 99.01, 302317], ["2024-07-24", 99.52, 341579], ["2024-07-25", 98.02, 114816], ["2024-07-26", 97.78, 93311], ["2024-07-29", 98.01, 156643], ["2024-07-30", 98.25, 76556], ["2024-07-31", 98.59, 84491], ["2024-08-01", 96.03, 77690], ["2024-08-02", 98.28, 79840], ["2024-08-05", 95.82, 113643], ["2024-08-06", 94.93, 74477], ["2024-08-07", 95.61, 54056], ["2024-08-08", 94.67, 58420], ["2024-08-09", 94.26, 46324], ["2024-08-12", 93.91, 79882], ["2024-08-13", 93.56, 57979], ["2024-08-14", 92.13, 36706], ["2024-08-16", 92.82, 25424], ["2024-08-19", 92.61, 30246], ["2024-08-20", 92.56, 40031], ["2024-08-21", 93.47, 62923], ["2024-08-22", 93.8, 73494], ["2024-08-23", 94.6, 31170], ["2024-08-26", 93.28, 53105], ["2024-08-27", 92.74, 50113], ["2024-08-28", 91.88, 54612], ["2024-08-29", 90.59, 54516], ["2024-08-30", 91.22, 37235], ["2024-09-02", 91.48, 35119], ["2024-09-03", 91.2, 34715], ["2024-09-04", 90.81, 23558], ["2024-09-05", 90.08, 68925], ["2024-09-06", 89.66, 42315], ["2024-09-09", 87.91, 49909], ["2024-09-10", 87.27, 75000], ["2024-09-11", 88.57, 43424], ["2024-09-12", 88.47, 30088], ["2024-09-13", 89.92, 251425], ["2024-09-16", 92.03, 108087], ["2024-09-17", 90.26, 47566], ["2024-09-18", 89.13, 26513], ["2024-09-19", 88.15, 29231], ["2024-09-20", 88.31, 17505], ["2024-09-23", 88.32, 31660], ["2024-09-24", 87.9, 21301], ["2024-09-25", 87.83, 9297], ["2024-09-26", 87.75, 30491], ["2024-09-27", 87.11, 45394], ["2024-09-30", 86.19, 55228], ["2024-10-01", 94.8, 159024], ["2024-10-03", 93.11, 307861], ["2024-10-04", 90.41, 82072], ["2024-10-07", 89.1, 107990], ["2024-10-08", 86.94, 173276], ["2024-10-09", 88.68, 26544], ["2024-10-10", 88.38, 19999], ["2024-10-11", 88.82, 25051], ["2024-10-14", 90.42, 35581], ["2024-10-15", 89.05, 16364], ["2024-10-16", 88.15, 29999], ["2024-10-17", 87.83, 18815], ["2024-10-18", 88.43, 18048], ["2024-10-21", 87.34, 25763], ["2024-10-22", 83.65, 34364], ["2024-10-23", 87.23, 53009], ["2024-10-24", 85.95, 17181], ["2024-10-25", 85.81, 92740], ["2024-10-28", 85.28, 22829], ["2024-10-29", 87.17, 20125], ["2024-10-30", 88.08, 22199], ["2024-10-31", 87.64, 12311], ["2024-11-01", 89.07, 7782], ["2024-11-04", 90.27, 67848], ["2024-11-05", 87.33, 55702], ["2024-11-06", 87.66, 44536], ["2024-11-07", 86.12, 55169], ["2024-11-08", 85.69, 10661], ["2024-11-11", 83.77, 42880], ["2024-11-12", 81.48, 39452], ["2024-11-13", 78.14, 45008], ["2024-11-14", 78.39, 46524], ["2024-11-18", 76.81, 35307], ["2024-11-19", 77.22, 19877], ["2024-11-21", 79.01, 26034], ["2024-11-22", 79.1, 21352], ["2024-11-25", 80.42, 15852], ["2024-11-26", 80.2, 10173], ["2024-11-27", 80.72, 14458], ["2024-11-28", 83.83, 28416], ["2024-11-29", 79.8, 80331], ["2024-12-02", 83.68, 39108], ["2024-12-03", 84.82, 42313], ["2024-12-04", 85.98, 37240], ["2024-12-05", 87.09, 23614], ["2024-12-06", 85.25, 46755], ["2024-12-09", 85.25, 21367], ["2024-12-10", 84.57, 12810], ["2024-12-11", 85.31, 52807], ["2024-12-12", 83.18, 28333], ["2024-12-13", 83.75, 13358], ["2024-12-16", 83.71, 38436], ["2024-12-17", 83.98, 22567], ["2024-12-18", 83.14, 19480], ["2024-12-19", 85.53, 47861], ["2024-12-20", 81.18, 41186], ["2024-12-23", 82.19, 19236], ["2024-12-24", 81.39, 11661], ["2024-12-26", 82.61, 30995], ["2024-12-27", 81.52, 29979], ["2024-12-30", 80.55, 20830], ["2024-12-31", 85.08, 52264], ["2025-01-01", 85.73, 26971], ["2025-01-02", 85.39, 23400], ["2025-01-03", 83.62, 22124], ["2025-01-06", 80.79, 17377], ["2025-01-07", 79.63, 25269], ["2025-01-08", 79.12, 18089], ["2025-01-09", 79.23, 15576], ["2025-01-10", 77.91, 57679], ["2025-01-13", 73.27, 49646], ["2025-01-14", 74.52, 16499], ["2025-01-15", 76.74, 18444], ["2025-01-16", 78.6, 11481], ["2025-01-17", 77.3, 10945], ["2025-01-20", 77.71, 14290], ["2025-01-21", 73.35, 134178], ["2025-01-22", 73.8, 22483], ["2025-01-23", 73.17, 16261], ["2025-01-24", 72.25, 23559], ["2025-01-27", 71.12, 19316], ["2025-01-28", 69.21, 20974], ["2025-01-29", 72.08, 29370], ["2025-01-30", 72.63, 12036], ["2025-01-31", 72.34, 26021], ["2025-02-01", 71.43, 25432], ["2025-02-03", 69.24, 56295], ["2025-02-04", 71.17, 23069], ["2025-02-05", 71.9, 18499], ["2025-02-06", 71.08, 14084], ["2025-02-07", 70.27, 13086], ["2025-02-10", 69.05, 14570], ["2025-02-11", 66.02, 28543], ["2025-02-12", 63.87, 36881], ["2025-02-13", 64.79, 22243], ["2025-02-14", 62.69, 22840], ["2025-02-17", 63.49, 57097], ["2025-02-18", 60.17, 49297], ["2025-02-19", 62.94, 18591], ["2025-02-20", 63.12, 23008], ["2025-02-21", 66.69, 48638], ["2025-02-24", 64.99, 33826], ["2025-02-25", 64.01, 7464], ["2025-02-27", 61.05, 135115], ["2025-02-28", 59.36, 21895], ["2025-03-03", 57.4, 29442], ["2025-03-04", 58.97, 18990], ["2025-03-05", 59.57, 32655], ["2025-03-06", 61.74, 24590], ["2025-03-07", 61.15, 20629], ["2025-03-10", 60.32, 19944], ["2025-03-11", 57.56, 30882], ["2025-03-12", 56.74, 32496], ["2025-03-13", 56.34, 49213], ["2025-03-17", 56.57, 28740], ["2025-03-18", 56.57, 0], ["2025-03-19", 56.62, 93726], ["2025-03-20", 56.52, 36668], ["2025-03-21", 56.53, 66842], ["2025-03-24", 57.74, 52457], ["2025-03-25", 56.29, 98672], ["2025-03-26", 55.11, 72549], ["2025-03-27", 53.5, 94598], ["2025-03-28", 49.14, 302153], ["2025-04-01", 52.31, 51175], ["2025-04-02", 53.18, 32506], ["2025-04-03", 56.02, 70532], ["2025-04-04", 55.01, 17065], ["2025-04-07", 53.11, 26793], ["2025-04-08", 54.66, 10113], ["2025-04-09", 53.36, 13399], ["2025-04-11", 54.27, 17497], ["2025-04-15", 55.38, 13057], ["2025-04-16", 55.47, 9485], ["2025-04-17", 57.81, 49153], ["2025-04-21", 59.1, 36850], ["2025-04-22", 58.81, 98080], ["2025-04-23", 58.6, 34280], ["2025-04-24", 58.61, 32842], ["2025-04-25", 56.94, 28214], ["2025-04-28", 57.93, 28766], ["2025-04-29", 57.26, 16356], ["2025-04-30", 55.82, 20834], ["2025-05-02", 56.78, 6804], ["2025-05-05", 56.74, 16763], ["2025-05-06", 55.36, 12005], ["2025-05-07", 53.21, 34653], ["2025-05-08", 54.61, 29151], ["2025-05-09", 53.11, 21877], ["2025-05-12", 55.82, 20320], ["2025-05-13", 55.94, 24355], ["2025-05-14", 57.21, 44822], ["2025-05-15", 56.86, 37401], ["2025-05-16", 57.69, 48005], ["2025-05-19", 58.37, 46370], ["2025-05-20", 57.29, 14770], ["2025-05-21", 57.49, 76899], ["2025-05-22", 58.01, 27720], ["2025-05-23", 58.83, 30708], ["2025-05-26", 59.07, 14117], ["2025-05-27", 60.89, 36918], ["2025-05-28", 63.02, 64076], ["2025-05-29", 63.84, 43781], ["2025-05-30", 64.66, 38651], ["2025-06-02", 65.38, 33017], ["2025-06-03", 67.34, 41697], ["2025-06-04", 67.64, 29395], ["2025-06-05", 68.12, 18623], ["2025-06-06", 69.44, 31321], ["2025-06-09", 67.95, 63142], ["2025-06-10", 68.62, 19430], ["2025-06-11", 68.57, 35193], ["2025-06-12", 68.52, 16374], ["2025-06-13", 66.55, 22380], ["2025-06-16", 66.75, 56077], ["2025-06-17", 67.52, 36229], ["2025-06-18", 68.56, 40692], ["2025-06-19", 66.59, 16451], ["2025-06-20", 66.5, 26489], ["2025-06-23", 66.73, 28994], ["2025-06-24", 66.1, 30979], ["2025-06-25", 66.13, 255344], ["2025-06-26", 66.52, 37195], ["2025-06-27", 67.15, 10795], ["2025-06-30", 66.82, 23230], ["2025-07-01", 66.82, 12168], ["2025-07-02", 66.86, 12871], ["2025-07-03", 66.95, 12484], ["2025-07-04", 66.88, 19693], ["2025-07-07", 66.7, 19036], ["2025-07-08", 66.78, 8486], ["2025-07-09", 66.5, 23572], ["2025-07-10", 66.82, 20103], ["2025-07-11", 66.63, 17775], ["2025-07-14", 67.62, 31721], ["2025-07-15", 67.06, 29376], ["2025-07-16", 67.76, 31456], ["2025-07-17", 67.9, 15358], ["2025-07-18", 69.76, 66082], ["2025-07-21", 71.23, 136645], ["2025-07-22", 67.9, 75442], ["2025-07-23", 68.06, 16750], ["2025-07-24", 70.14, 59439], ["2025-07-25", 69.76, 48608], ["2025-07-28", 69.47, 40149], ["2025-07-29", 70.41, 29211], ["2025-07-30", 68.16, 36227], ["2025-07-31", 68.2, 7729], ["2025-08-01", 67.76, 15043], ["2025-08-04", 67.15, 20365], ["2025-08-05", 64.38, 52981], ["2025-08-06", 63.14, 18946], ["2025-08-07", 62.99, 18006], ["2025-08-08", 62.77, 7735], ["2025-08-11", 62.23, 8854], ["2025-08-12", 61.78, 18831], ["2025-08-13", 62.97, 20941], ["2025-08-14", 62.13, 8040], ["2025-08-18", 64.62, 123842], ["2025-08-19", 70.78, 99879], ["2025-08-20", 72.12, 67019], ["2025-08-21", 72.02, 18720], ["2025-08-22", 73.35, 49541], ["2025-08-25", 80.68, 143181], ["2025-08-26", 88.74, 457787], ["2025-08-28", 84.53, 385429], ["2025-08-29", 85.4, 46623], ["2025-09-01", 88.29, 56333], ["2025-09-02", 92.7, 94621], ["2025-09-03", 95.03, 167360], ["2025-09-04", 99.78, 397482], ["2025-09-05", 104.76, 270155], ["2025-09-08", 99.52, 277482], ["2025-09-09", 97.52, 13888], ["2025-09-10", 95.56, 10710], ["2025-09-11", 94.3, 86245], ["2025-09-12", 92.41, 9190], ["2025-09-15", 94.25, 45750], ["2025-09-16", 96.13, 45412], ["2025-09-17", 98.05, 20552], ["2025-09-18", 98.05, 81187], ["2025-09-19", 96.09, 36225], ["2025-09-22", 94.16, 5155], ["2025-09-23", 92.27, 1172], ["2025-09-24", 91.1, 49039], ["2025-09-25", 89.27, 4565], ["2025-09-26", 87.48, 3826], ["2025-09-29", 85.73, 4524], ["2025-09-30", 84.05, 32072], ["2025-10-01", 82.36, 3934], ["2025-10-03", 80.71, 4304], ["2025-10-06", 82.3, 79916], ["2025-10-07", 83.94, 4898], ["2025-10-08", 83.9, 15978], ["2025-10-09", 85.55, 8914], ["2025-10-10", 83.83, 4027], ["2025-10-13", 80.43, 37265], ["2025-10-14", 77.21, 26451], ["2025-10-15", 75.91, 11671], ["2025-10-16", 74.99, 26151], ["2025-10-17", 74.64, 10534], ["2025-10-20", 74.72, 5312], ["2025-10-21", 78.13, 8742], ["2025-10-23", 76.29, 24922], ["2025-10-24", 73.72, 17121], ["2025-10-27", 70.68, 33933], ["2025-10-28", 72.2, 11288], ["2025-10-29", 72.38, 4593], ["2025-10-30", 72.46, 8391], ["2025-10-31", 72.1, 9202], ["2025-11-03", 72.02, 4478], ["2025-11-04", 72.42, 16965], ["2025-11-06", 70.12, 14058], ["2025-11-07", 72.43, 5470], ["2025-11-10", 76.05, 18211], ["2025-11-11", 79.85, 28130], ["2025-11-12", 80.08, 58494], ["2025-11-13", 77.24, 9185], ["2025-11-14", 77.06, 16158], ["2025-11-17", 76.41, 11471], ["2025-11-18", 77.32, 6764], ["2025-11-19", 75.67, 3692], ["2025-11-20", 76.42, 9650], ["2025-11-21", 73.85, 10446], ["2025-11-24", 71.51, 11650], ["2025-11-25", 73.0, 4426], ["2025-11-26", 72.6, 21117], ["2025-11-27", 73.02, 3589], ["2025-11-28", 72.0, 23552], ["2025-12-01", 70.62, 10228], ["2025-12-02", 73.1, 29789], ["2025-12-03", 72.38, 14088], ["2025-12-04", 72.58, 7343], ["2025-12-05", 73.76, 8357], ["2025-12-08", 72.07, 4684], ["2025-12-09", 70.55, 31043], ["2025-12-10", 70.07, 10726], ["2025-12-11", 70.44, 7995], ["2025-12-12", 73.52, 9000], ["2025-12-15", 70.46, 6944], ["2025-12-16", 72.14, 45876], ["2025-12-17", 70.45, 9224], ["2025-12-18", 69.97, 36720], ["2025-12-19", 67.45, 30390], ["2025-12-22", 67.64, 29708], ["2025-12-23", 68.2, 7746], ["2025-12-24", 69.72, 7821], ["2025-12-26", 68.9, 10092], ["2025-12-29", 67.52, 16328], ["2025-12-30", 66.25, 14505], ["2025-12-31", 66.52, 13447], ["2026-01-01", 65.65, 14061], ["2026-01-02", 67.02, 11543], ["2026-01-05", 66.11, 12218], ["2026-01-06", 66.08, 14060], ["2026-01-07", 68.08, 32086], ["2026-01-08", 69.09, 13886], ["2026-01-09", 72.3, 593879], ["2026-01-12", 67.6, 199892], ["2026-01-13", 68.24, 25453], ["2026-01-14", 66.24, 20304], ["2026-01-16", 66.69, 29200], ["2026-01-19", 64.39, 49198], ["2026-01-20", 61.56, 110286], ["2026-01-21", 59.71, 74809], ["2026-01-22", 61.56, 24487], ["2026-01-23", 59.19, 161132], ["2026-01-27", 58.21, 91835], ["2026-01-28", 58.4, 48104], ["2026-01-29", 54.96, 77158], ["2026-01-30", 57.18, 70769], ["2026-02-02", 57.99, 10552], ["2026-02-03", 59.38, 22073], ["2026-02-04", 58.87, 10746], ["2026-02-05", 58.63, 3706], ["2026-02-06", 58.56, 5027], ["2026-02-09", 60.0, 21395], ["2026-02-10", 59.44, 26353], ["2026-02-11", 59.36, 12134], ["2026-02-12", 56.7, 47641], ["2026-02-13", 55.32, 29249], ["2026-02-16", 56.28, 7738], ["2026-02-17", 56.8, 27824], ["2026-02-18", 57.65, 12858], ["2026-02-19", 55.38, 19387], ["2026-02-20", 55.49, 13113], ["2026-02-23", 54.36, 31062], ["2026-02-24", 55.06, 13080], ["2026-02-25", 55.39, 18568], ["2026-02-26", 55.4, 6626], ["2026-02-27", 55.54, 15586], ["2026-03-02", 53.06, 50428], ["2026-03-04", 52.57, 9236], ["2026-03-05", 52.74, 8100], ["2026-03-06", 53.79, 11031], ["2026-03-09", 52.75, 10368], ["2026-03-10", 53.88, 10840], ["2026-03-11", 52.57, 26111], ["2026-03-12", 53.77, 11698], ["2026-03-13", 51.96, 27607], ["2026-03-16", 50.99, 14602], ["2026-03-17", 53.08, 149069], ["2026-03-18", 53.91, 71190], ["2026-03-19", 53.86, 17345], ["2026-03-20", 52.79, 18893], ["2026-03-23", 48.25, 83148], ["2026-03-24", 44.69, 144306], ["2026-03-25", 44.08, 223937], ["2026-03-27", 42.24, 182178], ["2026-03-30", 40.79, 57917], ["2026-04-01", 42.82, 11713], ["2026-04-02", 44.96, 33005], ["2026-04-06", 47.2, 29187], ["2026-04-07", 49.56, 16543], ["2026-04-08", 52.03, 6058], ["2026-04-09", 54.63, 51870], ["2026-04-10", 57.36, 54725], ["2026-04-13", 56.74, 90168], ["2026-04-15", 57.42, 38348], ["2026-04-16", 57.91, 25518], ["2026-04-17", 57.92, 24494], ["2026-04-20", 56.6, 26907], ["2026-04-21", 55.67, 43973], ["2026-04-22", 56.08, 20046], ["2026-04-23", 54.92, 24659], ["2026-04-24", 55.47, 14686], ["2026-04-27", 56.35, 13048], ["2026-04-28", 56.03, 14469], ["2026-04-29", 56.32, 11288], ["2026-04-30", 56.31, 8995], ["2026-05-04", 56.32, 7581], ["2026-05-05", 55.33, 15246], ["2026-05-06", 55.56, 18337], ["2026-05-07", 56.55, 9759], ["2026-05-08", 57.62, 15577], ["2026-05-11", 55.84, 16416], ["2026-05-12", 55.89, 21067], ["2026-05-13", 57.48, 68025], ["2026-05-14", 58.24, 55962], ["2026-05-15", 55.81, 33492], ["2026-05-18", 54.68, 12563], ["2026-05-19", 55.12, 6420], ["2026-05-20", 55.23, 5440], ["2026-05-21", 56.05, 12126], ["2026-05-22", 55.11, 11545], ["2026-05-25", 55.25, 17502], ["2026-05-26", 55.78, 8678], ["2026-05-27", 56.17, 18178], ["2026-05-28", 56.17, 0], ["2026-05-29", 55.37, 9873], ["2026-06-01", 55.0, 8064], ["2026-06-02", 54.34, 12229], ["2026-06-03", 54.42, 21663], ["2026-06-04", 53.73, 7510], ["2026-06-05", 54.14, 15256], ["2026-06-08", 53.1, 29902], ["2026-06-09", 53.99, 9390], ["2026-06-10", 52.91, 32331], ["2026-06-11", 52.85, 5120], ["2026-06-12", 53.65, 9893], ["2026-06-15", 54.01, 27332], ["2026-06-16", 53.91, 8843], ["2026-06-17", 53.93, 7920], ["2026-06-18", 53.36, 25886], ["2026-06-19", 53.74, 7431], ["2026-06-22", 52.92, 24787], ["2026-06-23", 52.69, 14556], ["2026-06-24", 52.31, 20170], ["2026-06-25", 52.34, 8939], ["2026-06-26", 52.34, 0], ["2026-06-29", 52.75, 27971], ["2026-06-30", 52.48, 11417], ["2026-07-01", 52.19, 10972], ["2026-07-02", 52.03, 17048], ["2026-07-03", 51.11, 21418], ["2026-07-06", 49.92, 44578], ["2026-07-07", 49.98, 11657], ["2026-07-08", 49.97, 8152], ["2026-07-09", 49.39, 23789], ["2026-07-10", 49.15, 9993], ["2026-07-13", 49.4, 8070], ["2026-07-14", 49.35, 5772]], "monthly": [["2016-07-31", 184.0, 421532], ["2016-08-31", 156.0, 263058], ["2016-09-30", 175.0, 358243], ["2016-10-31", 157.0, 223988], ["2016-11-30", 148.0, 85798], ["2016-12-31", 173.0, 304166], ["2017-01-31", 214.0, 1177962], ["2017-02-28", 180.0, 194221], ["2017-03-31", 218.0, 441151], ["2017-04-30", 178.0, 195239], ["2017-05-31", 191.0, 151623], ["2017-06-30", 198.0, 474685], ["2017-07-31", 266.0, 736741], ["2017-08-31", 228.0, 1377118], ["2017-09-30", 249.0, 191925], ["2017-10-31", 240.0, 264028], ["2017-11-30", 274.0, 501758], ["2017-12-31", 262.0, 692625], ["2018-01-31", 219.0, 200530], ["2018-02-28", 194.0, 195908], ["2018-03-31", 218.0, 310274], ["2018-04-30", 197.0, 167197], ["2018-05-31", 182.0, 100163], ["2018-06-30", 179.0, 86743], ["2018-07-31", 169.0, 118186], ["2018-08-31", 131.0, 80144], ["2018-09-30", 124.0, 99834], ["2018-10-31", 117.0, 63244], ["2018-11-30", 119.0, 125018], ["2018-12-31", 91.0, 96286], ["2019-01-31", 93.0, 144916], ["2019-02-28", 103.0, 202188], ["2019-03-31", 89.0, 63785], ["2019-04-30", 93.0, 52162], ["2019-05-31", 80.0, 31343], ["2019-06-30", 52.0, 64661], ["2019-07-31", 50.0, 59458], ["2019-08-31", 53.0, 28059], ["2019-09-30", 48.0, 32304], ["2019-10-31", 46.0, 64617], ["2019-11-30", 40.0, 59968], ["2019-12-31", 43.0, 132235], ["2020-01-31", 37.0, 87796], ["2020-02-29", 32.0, 107672], ["2020-03-31", 62.0, 204471], ["2020-04-30", 76.0, 228675], ["2020-05-31", 203.0, 385051], ["2020-06-30", 112.0, 416991], ["2020-07-31", 106.0, 346759], ["2020-08-31", 98.0, 194650], ["2020-09-30", 96.0, 204552], ["2020-10-31", 97.0, 171281], ["2020-11-30", 120.0, 580026], ["2020-12-31", 107.0, 397690], ["2021-01-31", 112.0, 265686], ["2021-02-28", 108.0, 376152], ["2021-03-31", 107.0, 334926], ["2021-04-30", 176.0, 574719], ["2021-05-31", 316.0, 1117483], ["2021-06-30", 645.0, 1510693], ["2021-07-31", 455.0, 1225635], ["2021-08-31", 345.0, 898360], ["2021-09-30", 377.0, 1593531], ["2021-10-31", 319.0, 621820], ["2021-11-30", 323.0, 670906], ["2021-12-31", 329.0, 884814], ["2022-01-31", 274.0, 338191], ["2022-02-28", 293.0, 471590], ["2022-03-31", 252.0, 497476], ["2022-04-30", 194.0, 449392], ["2022-05-31", 160.0, 5178], ["2022-06-30", 151.0, 113016], ["2022-07-31", 119.0, 23915], ["2022-08-31", 147.0, 140776], ["2022-09-30", 115.0, 22302], ["2022-10-31", 131.0, 53280], ["2022-11-30", 118.0, 40545], ["2022-12-31", 168.0, 163882], ["2023-01-31", 108.0, 104715], ["2023-02-28", 99.0, 73726], ["2023-03-31", 99.0, 0], ["2023-04-30", 137.05, 97709], ["2023-05-31", 85.7, 3687760], ["2023-06-30", 105.0, 885387], ["2023-07-31", 102.75, 792358], ["2023-08-31", 97.35, 246910], ["2023-09-30", 93.85, 348597], ["2023-10-31", 94.6, 438083], ["2023-11-30", 108.95, 1755967], ["2023-12-31", 124.15, 1839104], ["2024-01-31", 96.85, 4816477], ["2024-02-29", 77.75, 3755608], ["2024-03-31", 96.25, 2310562], ["2024-04-30", 85.25, 1103806], ["2024-05-31", 97.35, 5548769], ["2024-06-30", 98.59, 2445473], ["2024-07-31", 91.22, 1191886], ["2024-08-31", 86.19, 1076751], ["2024-09-30", 87.64, 1321145], ["2024-10-31", 79.8, 667362], ["2024-11-30", 85.08, 652200], ["2024-12-31", 72.34, 631988], ["2025-01-31", 59.36, 670473], ["2025-02-28", 49.14, 1105246], ["2025-03-31", 55.82, 606997], ["2025-04-30", 64.66, 690166], ["2025-05-31", 66.82, 873047], ["2025-06-30", 68.2, 770381], ["2025-07-31", 85.4, 1581763], ["2025-08-31", 84.05, 1712945], ["2025-09-30", 72.1, 357547], ["2025-10-31", 72.0, 277506], ["2025-11-30", 66.52, 362054], ["2025-12-31", 57.18, 1674360], ["2026-01-31", 55.54, 370218], ["2026-02-28", 40.79, 1128004], ["2026-03-31", 56.31, 559700], ["2026-04-30", 55.37, 363787], ["2026-05-31", 52.48, 336610], ["2026-06-30", 49.35, 161449], ["2026-07-15", 49.19, 6413]], "weekly": [["2025-07-13", 69.76, 142272], ["2025-07-20", 69.76, 336884], ["2025-07-27", 67.76, 128359], ["2025-08-03", 62.77, 118033], ["2025-08-10", 62.13, 56666], ["2025-08-17", 73.35, 359001], ["2025-08-24", 85.4, 1033020], ["2025-08-31", 104.76, 985951], ["2025-09-07", 92.41, 397515], ["2025-09-14", 96.09, 229126], ["2025-09-21", 87.48, 63757], ["2025-09-28", 80.71, 44834], ["2025-10-05", 83.83, 113733], ["2025-10-12", 74.64, 112072], ["2025-10-19", 73.72, 56097], ["2025-10-26", 72.1, 67407], ["2025-11-02", 72.43, 40971], ["2025-11-09", 77.06, 130178], ["2025-11-16", 73.85, 42023], ["2025-11-23", 72.0, 64334], ["2025-11-30", 73.76, 69805], ["2025-12-07", 73.52, 63448], ["2025-12-14", 67.45, 129154], ["2025-12-21", 68.9, 55367], ["2025-12-28", 67.02, 69884], ["2026-01-04", 72.3, 666129], ["2026-01-11", 66.69, 274849], ["2026-01-18", 59.19, 419912], ["2026-01-25", 57.89, 303366], ["2026-02-01", 58.56, 52104], ["2026-02-08", 55.32, 136772], ["2026-02-15", 55.49, 80920], ["2026-02-22", 55.54, 84922], ["2026-03-01", 53.79, 78795], ["2026-03-08", 51.96, 86624], ["2026-03-15", 52.79, 271099], ["2026-03-22", 42.24, 633569], ["2026-03-29", 44.96, 102635], ["2026-04-05", 57.36, 158383], ["2026-04-12", 57.92, 178528], ["2026-04-19", 55.47, 130271], ["2026-04-26", 56.31, 47800], ["2026-05-03", 57.62, 66500], ["2026-05-10", 55.81, 194962], ["2026-05-17", 55.11, 48094], ["2026-05-24", 55.37, 54231], ["2026-05-31", 54.14, 64722], ["2026-06-07", 53.65, 86636], ["2026-06-14", 53.74, 77412], ["2026-06-21", 52.34, 68452], ["2026-06-28", 51.11, 88826], ["2026-07-05", 49.15, 98169], ["2026-07-12", 49.35, 13842], ["2026-07-15", 49.19, 6413]]}, "pe_band": null, "ev_band": null, "pb_band": {"series": [["2023-03-31", 2.57], ["2023-04-30", 3.56], ["2023-05-31", 2.22], ["2023-06-30", 2.72], ["2023-07-31", 2.67], ["2023-08-31", 2.53], ["2023-09-30", 2.57], ["2023-10-31", 2.59], ["2023-11-30", 2.98], ["2023-12-31", 3.4], ["2024-01-31", 2.65], ["2024-02-29", 2.13], ["2024-03-31", 2.99], ["2024-04-30", 2.65], ["2024-05-31", 3.02], ["2024-06-30", 3.06], ["2024-07-31", 2.83], ["2024-08-31", 2.68], ["2024-09-30", 3.39], ["2024-10-31", 3.09], ["2024-11-30", 3.29], ["2024-12-31", 2.8], ["2025-01-31", 2.3], ["2025-02-28", 1.9], ["2025-03-31", 3.56], ["2025-04-30", 4.12], ["2025-05-31", 4.26], ["2025-06-30", 4.35], ["2025-07-31", 5.45], ["2025-08-31", 5.36], ["2025-09-30", 4.6], ["2025-10-31", 4.59], ["2025-11-30", 4.24], ["2025-12-31", 3.65], ["2026-01-31", 3.54], ["2026-02-28", 2.6], ["2026-03-31", 6.43], ["2026-04-30", 6.32], ["2026-05-31", 5.99], ["2026-06-30", 5.63], ["2026-07-15", 5.62]], "median_5y": 3.09}, "ps_band": {"series": [["2024-03-31", 3.31], ["2024-04-30", 2.93], ["2024-05-31", 3.35], ["2024-06-30", 2.85], ["2024-07-31", 2.64], ["2024-08-31", 2.5], ["2024-09-30", 2.62], ["2024-10-31", 2.39], ["2024-11-30", 2.55], ["2024-12-31", 2.41], ["2025-01-31", 1.98], ["2025-02-28", 1.64], ["2025-03-31", 1.88], ["2025-04-30", 2.17], ["2025-05-31", 2.25], ["2025-06-30", 2.03], ["2025-07-31", 2.54], ["2025-08-31", 2.5], ["2025-09-30", 2.14], ["2025-10-31", 2.14], ["2025-11-30", 1.98], ["2025-12-31", 1.44], ["2026-01-31", 1.4], ["2026-02-28", 1.03], ["2026-03-31", 1.14], ["2026-04-30", 1.12], ["2026-05-31", 1.07], ["2026-06-30", 1.0], ["2026-07-15", 1.0]], "median_5y": 2.14}}