{"generated_at": "2026-07-11 13:52 UTC", "snapshot": {"symbol": "EUROPRATIK", "fetch_date": "2026-07-10 14:07:47", "name": null, "sector": "Basic Materials", "industry": "Building Materials", "price": 313.6, "mcap": 3205.0, "pe": 41.536423, "forward_pe": null, "pb": 10.362832, "book_value": 30.262, "roe": 27.8, "roa": 19.92, "de": 0.076, "div_yield": 0.13, "net_margin": 23.02, "op_margin": 25.36, "gross_margin": 47.77, "rev_growth": 28.1, "earn_growth": 45.8, "revenue": 3349617920.0, "net_income": 770920000.0, "total_debt": 244848000.0, "total_cash": 326020992.0, "free_cashflow": -92872752.0, "shares_out": 102200000.0, "wk52_high": 390.0, "wk52_low": 205.1, "beta": null}, "statements": {}, "documents": {"annual_reports": []}, "trend": {}, "shareholding": null, "prices": null}