{"generated_at": "2026-07-10 14:28 UTC", "snapshot": {"symbol": "ICICIGI", "fetch_date": "2026-07-10 14:13:17", "name": "ICICI Lombard General Insurance Company Limited", "sector": "Financial Services", "industry": "Insurance - Diversified", "price": 1826.2, "mcap": 91187.6, "pe": 33.035458, "forward_pe": 24.712223, "pb": 5.6641283, "book_value": 322.415, "roe": 17.85, "roa": 3.15, "de": 0.001, "div_yield": 0.78, "net_margin": 10.26, "op_margin": 11.44, "gross_margin": 23.6, "rev_growth": 12.2, "earn_growth": 6.7, "revenue": 270056898560.0, "net_income": 27719399424.0, "total_debt": 91600000.0, "total_cash": 77481000960.0, "free_cashflow": 34613288960.0, "shares_out": 499329702.0, "wk52_high": 2064.9, "wk52_low": 1629.5, "beta": 0.46}, "statements": {}}