{"generated_at": "2026-07-10 14:28 UTC", "snapshot": {"symbol": "IPCALAB", "fetch_date": "2026-07-10 14:15:05", "name": "Ipca Laboratories Limited", "sector": "Healthcare", "industry": "Drug Manufacturers - Specialty & Generic", "price": 1787.9, "mcap": 45359.8, "pe": 39.757614, "forward_pe": 27.231224, "pb": 5.6242194, "book_value": 317.893, "roe": 13.22, "roa": 8.08, "de": 0.085, "div_yield": 0.34, "net_margin": 11.83, "op_margin": 15.77, "gross_margin": 70.74, "rev_growth": 6.2, "earn_growth": 341.6, "revenue": 96463298560.0, "net_income": 11411200000.0, "total_debt": 8087600128.0, "total_cash": 11980099584.0, "free_cashflow": 7519925248.0, "shares_out": 253704218.0, "wk52_high": 1812.5, "wk52_low": 1251.6, "beta": 0.049}, "statements": {}}