{"generated_at": "2026-07-11 13:52 UTC", "snapshot": {"symbol": "MBLINFRA", "fetch_date": "2026-07-10 14:20:15", "name": "MBL Infrastructures Limited", "sector": "Industrials", "industry": "Engineering & Construction", "price": 26.02, "mcap": 401.8, "pe": null, "forward_pe": null, "pb": 0.40396824, "book_value": 64.411, "roe": -2.38, "roa": -0.92, "de": 1.035, "div_yield": null, "net_margin": -12.85, "op_margin": -15.47, "gross_margin": 92.54, "rev_growth": 67.4, "earn_growth": null, "revenue": 1760600064.0, "net_income": -226300000.0, "total_debt": 9894299648.0, "total_cash": 518700000.0, "free_cashflow": 443669504.0, "shares_out": 154429256.0, "wk52_high": 52.48, "wk52_low": 18.37, "beta": 0.476}, "statements": {}, "documents": {"annual_reports": []}, "trend": {}, "shareholding": null, "prices": null}