{"generated_at": "2026-07-10 14:44 UTC", "snapshot": {"symbol": "PSB", "fetch_date": "2026-07-10 14:26:08", "name": "Punjab & Sind Bank", "sector": "Financial Services", "industry": "Banks - Regional", "price": 24.99, "mcap": 17731.9, "pe": 13.435484, "forward_pe": null, "pb": 1.2642282, "book_value": 19.767, "roe": 9.62, "roa": 0.78, "de": null, "div_yield": 1.59, "net_margin": 27.95, "op_margin": 17.71, "gross_margin": 0.0, "rev_growth": -5.3, "earn_growth": 29.1, "revenue": 47294042112.0, "net_income": 13219342336.0, "total_debt": 163523264512.0, "total_cash": 17312800768.0, "free_cashflow": null, "shares_out": 7095585220.0, "wk52_high": 33.54, "wk52_low": 20.5, "beta": 0.494}, "statements": {}}