{"generated_at": "2026-07-10 14:28 UTC", "snapshot": {"symbol": "REPL", "fetch_date": "2026-07-10 14:28:17", "name": "Rudrabhishek Enterprises Limited", "sector": "Industrials", "industry": "Consulting Services", "price": 64.0, "mcap": 116.0, "pe": null, "forward_pe": null, "pb": 0.8324554, "book_value": 76.881, "roe": -7.82, "roa": -2.9, "de": 0.201, "div_yield": null, "net_margin": -13.6, "op_margin": -73.75, "gross_margin": 26.96, "rev_growth": -43.1, "earn_growth": null, "revenue": 833094976.0, "net_income": -113290000.0, "total_debt": 280319008.0, "total_cash": 57998000.0, "free_cashflow": -45687376.0, "shares_out": 18122500.0, "wk52_high": 184.8, "wk52_low": 60.0, "beta": 0.478}, "statements": {}}