{"generated_at": "2026-07-11 09:37 UTC", "snapshot": {"symbol": "VIVIMEDLAB", "fetch_date": "2026-07-10 14:38:49", "name": "Vivimed Labs Limited", "sector": "Healthcare", "industry": "Drug Manufacturers - Specialty & Generic", "price": 5.41, "mcap": 44.9, "pe": null, "forward_pe": null, "pb": -0.9358242, "book_value": -5.781, "roe": null, "roa": null, "de": null, "div_yield": null, "net_margin": -39.54, "op_margin": -97.25, "gross_margin": 54.72, "rev_growth": -56.3, "earn_growth": null, "revenue": 883920000.0, "net_income": -349489984.0, "total_debt": 3840460032.0, "total_cash": 10120000.0, "free_cashflow": null, "shares_out": 82913915.0, "wk52_high": 29.4, "wk52_low": 4.95, "beta": 0.735}, "statements": {}, "documents": {"annual_reports": []}, "trend": {}, "shareholding": null}